DHParser/__init__.py
DHParser/compile.pxd
DHParser/compile.py
DHParser/configuration.py
DHParser/dsl.py
DHParser/ebnf.pxd
DHParser/ebnf.py
DHParser/ebnf_flavors/__init__.py
DHParser/ebnf_flavors/heuristic.py
DHParser/error.pxd
DHParser/error.py
DHParser/externallibs/__init__.py
DHParser/externallibs/shadow_cython.py
DHParser/externallibs/shadow_cython.pyi
DHParser/externallibs/typing_extensions.py
DHParser/log.pxd
DHParser/log.py
DHParser/lsp.py
DHParser/nodetree.pxd
DHParser/nodetree.py
DHParser/parse.pxd
DHParser/parse.py
DHParser/parsers/HTMLParser.py
DHParser/parsers/XMLParser.py
DHParser/parsers/__init__.py
DHParser/pipeline.py
DHParser/preprocess.pxd
DHParser/preprocess.py
DHParser/py.typed
DHParser/scripts/XMLreflow.py
DHParser/scripts/__init__.py
DHParser/scripts/dhparser.py
DHParser/scripts/dhparser_cythonize.py
DHParser/scripts/dhparser_cythonize_stringview.py
DHParser/scripts/dhparser_rename.py
DHParser/scripts/update_lsp.py
DHParser/server.py
DHParser/stringview.pxd
DHParser/stringview.py
DHParser/templates/DSLApp.pyi
DHParser/templates/DSLApp.pyi_old
DHParser/templates/DSLApp_old.pyi
DHParser/templates/DSLConfig.ini
DHParser/templates/DSLParser.pyi
DHParser/templates/DSLServer.pyi
DHParser/templates/README.txt
DHParser/templates/example_01_test_Regular_Expressions.ini
DHParser/templates/example_02_test_Structure_and_Components.ini
DHParser/templates/example_DSL.ebnf
DHParser/templates/readme_template.md
DHParser/templates/tst_DSL_grammar.pyi
DHParser/testing.pxd
DHParser/testing.py
DHParser/toolkit.pxd
DHParser/toolkit.py
DHParser/trace.pxd
DHParser/trace.py
DHParser/transform.pxd
DHParser/transform.py
DHParser/ts2python/__init__.py
DHParser/ts2python/json_validation.py
DHParser/ts2python/singledispatch_shim.py
DHParser/ts2python/ts2pythonParser.ini
DHParser/ts2python/ts2pythonParser.py
DHParser/ts2python/typeddict_shim.py
DHParser/ts2python/typing_extensions.py
DHParser/validate.py
DHParser/versionnumber.py
dhparser-1.9.2.dist-info/METADATA
dhparser-1.9.2.dist-info/WHEEL
dhparser-1.9.2.dist-info/entry_points.txt
dhparser-1.9.2.dist-info/licenses/LICENSE
dhparser-1.9.2.dist-info/RECORD
