Metadata-Version: 2.4
Name: DHParser
Version: 1.9.2
Summary: Parser Generator and DSL-construction-kit
License: Apache-2.0
License-File: LICENSE
Keywords: parser,parser generator,domain specific languages,Digital Humanities,parsing expression grammar,formal grammar,EBNF,SXML,XML
Author: Eckhart Arnold
Author-email: eckhart.arnold@posteo.de
Requires-Python: >=3.7
Classifier: Development Status :: 5 - Production/Stable
Classifier: Environment :: Console
Classifier: Intended Audience :: Developers
Classifier: License :: OSI Approved :: Apache Software License
Classifier: Operating System :: OS Independent
Classifier: Programming Language :: Python :: 3
Classifier: Programming Language :: Python :: 3.7
Classifier: Programming Language :: Python :: 3.8
Classifier: Programming Language :: Python :: 3.9
Classifier: Programming Language :: Python :: 3.10
Classifier: Programming Language :: Python :: 3.11
Classifier: Programming Language :: Python :: 3.12
Classifier: Programming Language :: Python :: 3.13
Classifier: Programming Language :: Python :: 3.14
Classifier: Programming Language :: Python :: Implementation :: CPython
Classifier: Programming Language :: Python :: Implementation :: PyPy
Classifier: Topic :: Software Development :: Code Generators
Classifier: Topic :: Software Development :: Compilers
Classifier: Topic :: Text Processing :: Markup
Provides-Extra: cython
Provides-Extra: pytest
Provides-Extra: regex
Provides-Extra: sphinx
Requires-Dist: cython (>=3.0) ; extra == "cython"
Requires-Dist: pytest (>=5.0) ; extra == "pytest"
Requires-Dist: regex ; extra == "regex"
Requires-Dist: sphinx (>=8.0) ; (python_version >= "3.10") and (extra == "sphinx")
Project-URL: Bug Tracker, https://github.com/jecki/DHParser/issues
Project-URL: Documentation, https://dhparser.readthedocs.io/en/latest/
Project-URL: Homepage, https://gitlab.lrz.de/badw-it/DHParser
Project-URL: Repository, https://gitlab.lrz.de/badw-it/DHParser
